odoo/addons/pos_ticket_logo/README.rst
odoo/addons/pos_ticket_logo/__init__.py
odoo/addons/pos_ticket_logo/__manifest__.py
odoo/addons/pos_ticket_logo/i18n/ca.po
odoo/addons/pos_ticket_logo/i18n/es.po
odoo/addons/pos_ticket_logo/i18n/pos_ticket_logo.pot
odoo/addons/pos_ticket_logo/readme/CONFIGURE.rst
odoo/addons/pos_ticket_logo/readme/CONTRIBUTORS.rst
odoo/addons/pos_ticket_logo/readme/DESCRIPTION.rst
odoo/addons/pos_ticket_logo/readme/USAGE.rst
odoo/addons/pos_ticket_logo/static/description/icon.png
odoo/addons/pos_ticket_logo/static/description/index.html
odoo/addons/pos_ticket_logo/static/src/js/models.js
odoo/addons/pos_ticket_logo/static/src/xml/pos.xml
odoo/addons/pos_ticket_logo/templates/assets.xml
odoo11_addon_pos_ticket_logo-11.0.1.0.0.99.dev6.dist-info/METADATA
odoo11_addon_pos_ticket_logo-11.0.1.0.0.99.dev6.dist-info/WHEEL
odoo11_addon_pos_ticket_logo-11.0.1.0.0.99.dev6.dist-info/top_level.txt
odoo11_addon_pos_ticket_logo-11.0.1.0.0.99.dev6.dist-info/RECORD
